MANIFEST.in
README.rst
setup.cfg
setup.py
andrototal_cli.egg-info/PKG-INFO
andrototal_cli.egg-info/SOURCES.txt
andrototal_cli.egg-info/dependency_links.txt
andrototal_cli.egg-info/entry_points.txt
andrototal_cli.egg-info/requires.txt
andrototal_cli.egg-info/top_level.txt
local_worker/__init__.py
local_worker/scan_cli.py
local_worker/core/__init__.py
local_worker/core/lockfile.py
local_worker/core/task.py
local_worker/core/task_manager.py
local_worker/core/utils.py
local_worker/core/virtualdevice.py