Metadata-Version: 1.1
Name: andrototal-cli
Version: 1.69
Summary: local_worker package
Home-page: https://github.com/andrototal-org/andrototal-cli/
Author: andrototal-org
Author-email: UNKNOWN
License: GPL
Download-URL: http://github.com/andrototal-org/andrototal-cli/tarball/master/#egg=andrototal-cli-1.0
Platform: UNKNOWN
Classifier: Intended Audience :: Developers
Classifier: License :: OSI Approved :: GNU General Public License v3 (GPLv3)
Classifier: Operating System :: OS Independent
Classifier: Programming Language :: Python
Classifier: Programming Language :: Python :: 2
Classifier: Programming Language :: Python :: 2.3
Classifier: Programming Language :: Python :: 2.4
Classifier: Programming Language :: Python :: 2.5
Classifier: Programming Language :: Python :: 2.6
Classifier: Programming Language :: Python :: 2.7
